{
  "name": "kanka-foundry",
  "title": "Kanka-Foundry",
  "description": "<p>This is a module which integrates <a href=\"https://kanka.io\">Kanka.io</a>, a free worldbuilding and tabletop RPG campaign management tool, with Foundry Virtual Tabletop, allowing you to import entities written in Kanka as journal entries into Foundry VTT. This module imports full Kanka entities, including their main entry text, image, relations and other data. This is not an official module, but a fan creation by someone who uses both Kanka and Foundry VTT.</p>",
  "url": "https://github.com/eXaminator/kanka-foundry",
  "manifest": "https://github.com/eXaminator/kanka-foundry/releases/latest/download/module.json",
  "download": "https://github.com/eXaminator/kanka-foundry/releases/download/__VERSION__/module.zip",
  "version": "__VERSION__",
  "author": "eXaminator",
  "authors": [
    {
      "name": "eXaminator",
      "discord": "eXaminator#0079",
      "twitter": "@eXXaminator"
    }
  ],
  "scripts": ["sheetClassShim.js"],
  "esmodules": ["index.js"],
  "styles": ["index.css"],
  "languages": [
    {
      "lang": "en",
      "name": "English",
      "path": "lang/en.json"
    },
    {
      "lang": "de",
      "name": "Deutsch",
      "path": "lang/de.json"
    }
  ],
  "minimumCoreVersion": "0.8.6",
  "compatibleCoreVersion": "0.8.8",
  "manifestPlusVersion": "1.0.0",
  "media": [
    {
      "type": "cover",
      "url": "https://raw.githubusercontent.com/eXaminator/kanka-foundry/main/docs/assets/cover.png"
    },
    {
      "type": "icon",
      "url": "https://raw.githubusercontent.com/eXaminator/kanka-foundry/main/docs/assets/kanka-logo.png"
    },
    {
      "type": "screenshot",
      "url": "https://raw.githubusercontent.com/eXaminator/kanka-foundry/main/docs/assets/character.png"
    },
    {
      "type": "screenshot",
      "url": "https://raw.githubusercontent.com/eXaminator/kanka-foundry/main/docs/assets/character_relations.png"
    },
    {
      "type": "screenshot",
      "url": "https://raw.githubusercontent.com/eXaminator/kanka-foundry/main/docs/assets/browser.png"
    },
    {
      "type": "screenshot",
      "url": "https://raw.githubusercontent.com/eXaminator/kanka-foundry/main/docs/assets/kanka-button.png"
    }
  ],
  "allowBugReporter": true,
  "bugs": "https://github.com/eXaminator/kanka-foundry/issues"
}
